INSTALL
LICENSE
MANIFEST.in
README
requirements.txt
setup.cfg
setup.py
tests.py
docs/Makefile
docs/conf.py
docs/index.rst
docs/make.bat
docs/build/html/_static/file.png
docs/build/html/_static/minus.png
docs/build/html/_static/plus.png
docs/intro/faq.rst
docs/intro/hackerguide.rst
docs/intro/install.rst
docs/intro/overview.rst
eyes.egg-info/PKG-INFO
eyes.egg-info/SOURCES.txt
eyes.egg-info/dependency_links.txt
eyes.egg-info/not-zip-safe
eyes.egg-info/requires.txt
eyes.egg-info/top_level.txt
eyeswebapp/__init__.py
eyeswebapp/context_processors.py
eyeswebapp/initial_data.json
eyeswebapp/manage.py
eyeswebapp/modeltestdata.json
eyeswebapp/setsuperuserpassword.py
eyeswebapp/settings.py
eyeswebapp/urls.py
eyeswebapp/api/__init__.py
eyeswebapp/api/handlers.py
eyeswebapp/api/models.py
eyeswebapp/api/urls.py
eyeswebapp/api/tests/__init__.py
eyeswebapp/api/tests/monitor.py
eyeswebapp/core/__init__.py
eyeswebapp/core/admin.py
eyeswebapp/core/models.py
eyeswebapp/core/urls.py
eyeswebapp/core/views.py
eyeswebapp/core/migrations/0001_initial.py
eyeswebapp/core/migrations/0002_removehostip.py
eyeswebapp/core/migrations/0003_move_host_to_new_model.py
eyeswebapp/core/migrations/0004_remove_timeout_from_model.py
eyeswebapp/core/migrations/0005_rename_kind_to_plugin_name.py
eyeswebapp/core/migrations/0006_add_passive_to_monitor_model.py
eyeswebapp/core/migrations/0007_set_basic_passive_data.py
eyeswebapp/core/migrations/__init__.py
eyeswebapp/core/tests/__init__.py
eyeswebapp/core/tests/datastore.py
eyeswebapp/core/tests/host.py
eyeswebapp/core/tests/monitor.py
eyeswebapp/core/tests/testpyrrd.py
eyeswebapp/core/tests/util.py
eyeswebapp/core/tests/views.py
eyeswebapp/static_media/css/common.css
eyeswebapp/templates/404.html
eyeswebapp/templates/500.html
eyeswebapp/templates/base.html
eyeswebapp/templates/documentation.html
eyeswebapp/templates/frontpage.html
eyeswebapp/templates/visualtest.html
eyeswebapp/templates/admin/base_site.html
eyeswebapp/templates/core/datastore_detail.html
eyeswebapp/templates/core/host_detail.html
eyeswebapp/templates/core/index.html
eyeswebapp/templates/core/monitor_detail.html
