Metadata-Version: 1.0
Name: eyes
Version: 0.4
Summary: Eyes is a project to enable quick, simple, and API enabled monitoring and data collection
Home-page: http://bitbucket.org/heckj/eyes/
Author: Joseph Heck
Author-email: heckj@mac.com
License: UNKNOWN
Platform: UNKNOWN
Classifier: Development Status :: 3 - Alpha
Classifier: Environment :: Web Environment
Classifier: Framework :: Django
Classifier: License :: OSI Approved :: Apache Software License
Classifier: Topic :: System :: Monitoring
Classifier: Intended Audience :: Developers
Classifier: Programming Language :: Python
Classifier: Operating System :: OS Independent
